pyspark_explorer/__init__.py
pyspark_explorer/data_table.py
pyspark_explorer/explorer.py
pyspark_explorer/run.py
pyspark_explorer/ui.py
pyspark_explorer/ui.tcss
pyspark_explorer/ui_busy_screen.py
pyspark_explorer/ui_filters_screen.py
pyspark_explorer/ui_options_screen.py
pyspark_explorer-0.2.2.dist-info/METADATA
pyspark_explorer-0.2.2.dist-info/WHEEL
pyspark_explorer-0.2.2.dist-info/entry_points.txt
pyspark_explorer-0.2.2.dist-info/licenses/LICENSE
pyspark_explorer-0.2.2.dist-info/RECORD
