Metadata-Version: 2.4
Name: pyspark-explorer
Version: 0.2.2
Summary: Explore data files with pyspark
Project-URL: Homepage, https://github.com/krzys9876/pyspark_explorer
Project-URL: Repository, https://github.com/krzys9876/pyspark_explorer
Author-email: Krzysztof Ruta <krzys9876@gmail.com>
Maintainer-email: Krzysztof Ruta <krzys9876@gmail.com>
License: MIT License
License-File: LICENSE
Keywords: data,explorer,pyspark,spark
Classifier: Development Status :: 4 - Beta
Classifier: Programming Language :: Python
Requires-Python: >=3.11
Requires-Dist: pyspark>=3.5.1
Requires-Dist: textual>=1.0.0
